{
  "common": {
    "name": "xbox",
    "version": "0.6.4",
    "news": {
      "0.6.4": {
        "en": "js-controller v3 compatibility",
        "de": "Kompatibilität mit js-controller v3",
        "ru": "совместимость с js-контроллером v3",
        "pt": "Compatibilidade com js-controller v3",
        "nl": "js-controller v3 compatibiliteit",
        "fr": "compatibilité js-controller v3",
        "it": "Compatibilità js-controller v3",
        "es": "Compatibilidad con js-controller v3",
        "pl": "Kompatybilność z js-controller v3",
        "zh-cn": "js-controller v3兼容性"
      },
      "0.6.3": {
        "en": "we now try specific python versions first on install and auth fixed",
        "de": "Wir versuchen jetzt bestimmte Python-Versionen zuerst bei der Installation und Authentifizierung behoben",
        "ru": "Теперь мы сначала попробуем установить конкретные версии Python при установке и авторизации.",
        "pt": "agora tentamos primeiro versões específicas do python na instalação e autenticação corrigidas",
        "nl": "we proberen nu eerst specifieke python-versies bij installatie en auth fixed",
        "fr": "nous essayons maintenant des versions spécifiques de python d'abord sur l'installation et l'authentification corrigée",
        "it": "ora proviamo prima versioni specifiche di Python su install e auth fixed",
        "es": "ahora intentamos versiones específicas de Python primero en la instalación y auth arreglado",
        "pl": "teraz próbujemy konkretnych wersji Pythona po instalacji i naprawiono uwierzytelnianie",
        "zh-cn": "我们现在首先在安装和身份验证固定后尝试特定的python版本"
      },
      "0.6.1": {
        "en": "fixes for compact mode, improved error handling, translations",
        "de": "Korrekturen für den kompakten Modus, verbesserte Fehlerbehandlung, Übersetzungen",
        "ru": "исправления для компактного режима, улучшенная обработка ошибок, переводы",
        "pt": "correções para o modo compacto, manipulação aprimorada de erros, traduções",
        "nl": "oplossingen voor compacte modus, verbeterde foutafhandeling, vertalingen",
        "fr": "corrections pour le mode compact, gestion améliorée des erreurs, traductions",
        "it": "correzioni per la modalità compatta, una migliore gestione degli errori, traduzioni",
        "es": "correcciones para el modo compacto, manejo mejorado de errores, traducciones",
        "pl": "poprawki trybu kompaktowego, ulepszona obsługa błędów, tłumaczenia",
        "zh-cn": "修复了紧凑模式，改进的错误处理，翻译"
      },
      "0.6.0": {
        "en": "dependency upgrade, python 3.6 required",
        "de": "Abhängigkeits-Upgrade, Python 3.6 erforderlich",
        "ru": "обновление зависимостей, требуется Python 3.6",
        "pt": "atualização de dependência, requer python 3.6",
        "nl": "afhankelijkheid upgrade, python 3.6 vereist",
        "fr": "mise à niveau des dépendances, python 3.6 requis",
        "it": "aggiornamento delle dipendenze, richiesto python 3.6",
        "es": "actualización de dependencia, requiere Python 3.6",
        "pl": "aktualizacja zależności, wymagany Python 3.6",
        "zh-cn": "依赖项升级，需要python 3.6"
      },
      "0.5.12": {
        "en": "we let js-controller know which apt packages are required",
        "de": "wir teilen js-controller mit, welche apt-pakete benötigt werden",
        "ru": "мы сообщаем js-controller, какие пакеты apt требуются",
        "pt": "nós informamos ao js-controller quais pacotes apt são necessários",
        "nl": "we laten js-controller weten welke apt-pakketten nodig zijn",
        "fr": "nous informons js-controller des packages apt requis",
        "it": "facciamo sapere a js-controller quali pacchetti apt sono richiesti",
        "es": "le informamos a js-controller qué paquetes apt son necesarios",
        "pl": "informujemy sterownik js, które pakiety apt są wymagane",
        "zh-cn": "我们让js-controller知道需要哪些apt软件包"
      },
      "0.5.11": {
        "en": "we not try to install apt packages any longer if already installed",
        "de": "Wir versuchen nicht mehr, apt-Pakete zu installieren, wenn diese bereits installiert sind",
        "ru": "мы больше не пытаемся устанавливать пакеты apt, если они уже установлены",
        "pt": "não tentamos instalar mais pacotes apt se já estiver instalado",
        "nl": "we proberen niet langer apt-pakketten te installeren als deze al zijn geïnstalleerd",
        "fr": "nous n'essayons plus d'installer des paquets apt s'ils sont déjà installés",
        "it": "non proviamo più a installare i pacchetti apt se già installati",
        "es": "ya no intentamos instalar paquetes apt si ya están instalados",
        "pl": "nie próbujemy już instalować pakietów apt, jeśli są już zainstalowane",
        "zh-cn": "如果已经安装，我们不会再尝试安装apt软件包"
      },
      "0.5.8": {
        "en": "increased stopTimeout to successfully shut down adapter on windows based systems",
        "de": "StopTimeout wurde erhöht, um den Adapter auf Windows-basierten Systemen erfolgreich herunterzufahren",
        "ru": "увеличено значение stopTimeout для успешного выключения адаптера в системах на базе Windows",
        "pt": "aumento de stopTimeout para desligar com sucesso o adaptador em sistemas baseados em Windows",
        "nl": "verhoogde stopTimeout om adapter op Windows-gebaseerde systemen succesvol af te sluiten",
        "fr": "stopTimeout augmenté pour arrêter l'adaptateur avec succès sur les systèmes Windows",
        "it": "stopTimeout aumentato per chiudere correttamente l'adattatore su sistemi basati su Windows",
        "es": "Incremento de stopTimeout para apagar con éxito el adaptador en sistemas basados en Windows",
        "pl": "zwiększono stopTimeout, aby pomyślnie zamknąć adapter w systemach opartych na systemie Windows",
        "zh-cn": "增加stopTimeout以成功关闭基于Windows的系统上的适配器"
      }
    },
    "title": "Xbox",
    "desc": {
      "en": "Control your Xbox One (X)",
      "de": "Steuere deine Xbox One (X)"
    },
    "authors": [
      "Moritz Heusinger <moritz.heusinger@gmail.com>"
    ],
    "platform": "Javascript/Node.js",
    "mode": "daemon",
    "icon": "xbox.png",
    "materialize": true,
    "enabled": true,
    "compact": true,
    "extIcon": "https://raw.githubusercontent.com/foxriver76/ioBroker.xbox/master/admin/xbox.png",
    "keywords": [
      "xbox",
      "gaming",
      "playstation"
    ],
    "osDependencies": {
      "linux": ["build-essential", "libssl-dev", "libffi-dev", "python3-dev"]
    },
    "readme": "https://github.com/foxriver76/ioBroker.xbox/blob/master/README.md",
    "loglevel": "info",
    "type": "multimedia",
    "connectionType": "local",
    "dataSource": "poll",
    "license": "MIT",
    "messagebox": false,
    "stopTimeout": 2000,
    "docs": {
      "de": "docs/de/README.md"
    }
  },
  "native": {
    "ip": "",
    "liveId": "",
    "mail": "",
    "password": ""
  },
  "protectedNative": [
    "mail",
    "password"
  ],
  "objects": [],
  "instanceObjects": [
    {
      "_id": "info",
      "type": "channel",
      "common": {
        "name": "Information"
      },
      "native": {}
    },
    {
      "_id": "info.connection",
      "type": "state",
      "common": {
        "role": "indicator.connected",
        "name": "If connected to Xbox",
        "type": "boolean",
        "read": true,
        "write": false,
        "def": false
      },
      "native": {}
    },
    {
      "_id": "media",
      "type": "channel",
      "common": {
        "name": "Media"
      },
      "native": {}
    },
    {
      "_id": "gamepad",
      "type": "channel",
      "common": {
        "name": "Gamepad"
      },
      "native": {}
    },
    {
      "_id": "settings",
      "type": "channel",
      "common": {
        "name": "Settings and device commands"
      },
      "native": {}
    },
    {
      "_id": "settings.power",
      "type": "state",
      "common": {
        "role": "switch.power",
        "name": "Console power status",
        "type": "boolean",
        "read": true,
        "write": true,
        "def": false
      },
      "native": {}
    },
    {
      "_id": "gamepad.rightShoulder",
      "type": "state",
      "common": {
        "role": "button",
        "name": "Right Shoulder Button",
        "type": "boolean",
        "read": true,
        "write": true,
        "def": false
      },
      "native": {}
    },
    {
      "_id": "gamepad.leftShoulder",
      "type": "state",
      "common": {
        "role": "button",
        "name": "Left Shoulder Button",
        "type": "boolean",
        "read": true,
        "write": true,
        "def": false
      },
      "native": {}
    },
    {
      "_id": "gamepad.leftThumbstick",
      "type": "state",
      "common": {
        "role": "button",
        "name": "Left Thumbstick Button",
        "type": "boolean",
        "read": true,
        "write": true,
        "def": false
      },
      "native": {}
    },
    {
      "_id": "gamepad.rightThumbstick",
      "type": "state",
      "common": {
        "role": "button",
        "name": "Right Thumbstick Button",
        "type": "boolean",
        "read": true,
        "write": true,
        "def": false
      },
      "native": {}
    },
    {
      "_id": "gamepad.enroll",
      "type": "state",
      "common": {
        "role": "button",
        "name": "Enroll Button",
        "type": "boolean",
        "read": true,
        "write": true,
        "def": false
      },
      "native": {}
    },
    {
      "_id": "gamepad.view",
      "type": "state",
      "common": {
        "role": "button",
        "name": "View Button",
        "type": "boolean",
        "read": true,
        "write": true,
        "def": false
      },
      "native": {}
    },
    {
      "_id": "gamepad.menu",
      "type": "state",
      "common": {
        "role": "button",
        "name": "Menu Button",
        "type": "boolean",
        "read": true,
        "write": true,
        "def": false
      },
      "native": {}
    },
    {
      "_id": "gamepad.nexus",
      "type": "state",
      "common": {
        "role": "button",
        "name": "Nexus Button",
        "type": "boolean",
        "read": true,
        "write": true,
        "def": false
      },
      "native": {}
    },
    {
      "_id": "gamepad.a",
      "type": "state",
      "common": {
        "role": "button",
        "name": "A Button",
        "type": "boolean",
        "read": true,
        "write": true,
        "def": false
      },
      "native": {}
    },
    {
      "_id": "gamepad.b",
      "type": "state",
      "common": {
        "role": "button",
        "name": "B Button",
        "type": "boolean",
        "read": true,
        "write": true,
        "def": false
      },
      "native": {}
    },
    {
      "_id": "gamepad.x",
      "type": "state",
      "common": {
        "role": "button",
        "name": "X Button",
        "type": "boolean",
        "read": true,
        "write": true,
        "def": false
      },
      "native": {}
    },
    {
      "_id": "gamepad.y",
      "type": "state",
      "common": {
        "role": "button",
        "name": "Y Button",
        "type": "boolean",
        "read": true,
        "write": true,
        "def": false
      },
      "native": {}
    },
    {
      "_id": "gamepad.dpadUp",
      "type": "state",
      "common": {
        "role": "button",
        "name": "DPad Button",
        "type": "boolean",
        "read": true,
        "write": true,
        "def": false
      },
      "native": {}
    },
    {
      "_id": "gamepad.clear",
      "type": "state",
      "common": {
        "role": "button",
        "name": "Clear Button",
        "type": "boolean",
        "read": true,
        "write": true,
        "def": false
      },
      "native": {}
    },
    {
      "_id": "gamepad.dpadRight",
      "type": "state",
      "common": {
        "role": "button",
        "name": "DPad Right",
        "type": "boolean",
        "read": true,
        "write": true,
        "def": false
      },
      "native": {}
    },
    {
      "_id": "gamepad.dpadLeft",
      "type": "state",
      "common": {
        "role": "button",
        "name": "DPad Left",
        "type": "boolean",
        "read": true,
        "write": true,
        "def": false
      },
      "native": {}
    },
    {
      "_id": "gamepad.dpadDown",
      "type": "state",
      "common": {
        "role": "button",
        "name": "DPad Down",
        "type": "boolean",
        "read": true,
        "write": true,
        "def": false
      },
      "native": {}
    },
    {
      "_id": "media.play",
      "type": "state",
      "common": {
        "role": "button",
        "name": "Play",
        "type": "boolean",
        "read": true,
        "write": true,
        "def": false
      },
      "native": {}
    },
    {
      "_id": "media.pause",
      "type": "state",
      "common": {
        "role": "button",
        "name": "Pause",
        "type": "boolean",
        "read": true,
        "write": true,
        "def": false
      },
      "native": {}
    },
    {
      "_id": "media.record",
      "type": "state",
      "common": {
        "role": "button",
        "name": "Record",
        "type": "boolean",
        "read": true,
        "write": true,
        "def": false
      },
      "native": {}
    },
    {
      "_id": "media.previousTrack",
      "type": "state",
      "common": {
        "role": "button",
        "name": "Previous Track",
        "type": "boolean",
        "read": true,
        "write": true,
        "def": false
      },
      "native": {}
    },
    {
      "_id": "media.playPause",
      "type": "state",
      "common": {
        "role": "button",
        "name": "Play/Pause",
        "type": "boolean",
        "read": true,
        "write": true,
        "def": false
      },
      "native": {}
    },
    {
      "_id": "media.seek",
      "type": "state",
      "common": {
        "role": "number.position",
        "name": "Seek",
        "type": "number",
        "read": true,
        "write": true,
        "def": false
      },
      "native": {}
    },
    {
      "_id": "media.channelUp",
      "type": "state",
      "common": {
        "role": "button",
        "name": "Channel Up",
        "type": "boolean",
        "read": true,
        "write": true,
        "def": false
      },
      "native": {}
    },
    {
      "_id": "media.nextTrack",
      "type": "state",
      "common": {
        "role": "button",
        "name": "Next Track",
        "type": "boolean",
        "read": true,
        "write": true,
        "def": false
      },
      "native": {}
    },
    {
      "_id": "media.channelDown",
      "type": "state",
      "common": {
        "role": "button",
        "name": "Channel Down",
        "type": "boolean",
        "read": true,
        "write": true,
        "def": false
      },
      "native": {}
    },
    {
      "_id": "media.menu",
      "type": "state",
      "common": {
        "role": "button",
        "name": "Menu",
        "type": "boolean",
        "read": true,
        "write": true,
        "def": false
      },
      "native": {}
    },
    {
      "_id": "media.back",
      "type": "state",
      "common": {
        "role": "button",
        "name": "Back",
        "type": "boolean",
        "read": true,
        "write": true,
        "def": false
      },
      "native": {}
    },
    {
      "_id": "media.rewind",
      "type": "state",
      "common": {
        "role": "button",
        "name": "Rewind",
        "type": "boolean",
        "read": true,
        "write": true,
        "def": false
      },
      "native": {}
    },
    {
      "_id": "media.view",
      "type": "state",
      "common": {
        "role": "button",
        "name": "View",
        "type": "boolean",
        "read": true,
        "write": true,
        "def": false
      },
      "native": {}
    },
    {
      "_id": "media.fastForward",
      "type": "state",
      "common": {
        "role": "button",
        "name": "Fast Forward",
        "type": "boolean",
        "read": true,
        "write": true,
        "def": false
      },
      "native": {}
    },
    {
      "_id": "media.stop",
      "type": "state",
      "common": {
        "role": "button",
        "name": "Stop",
        "type": "boolean",
        "read": true,
        "write": true,
        "def": false
      },
      "native": {}
    },
    {
      "_id": "settings.inputText",
      "type": "state",
      "common": {
        "role": "text.input",
        "name": "Input Text",
        "type": "string",
        "read": true,
        "write": true
      },
      "native": {}
    },
    {
      "_id": "settings.launchTitle",
      "type": "state",
      "common": {
        "role": "text.launch",
        "name": "Launch Title",
        "type": "string",
        "read": true,
        "write": true
      },
      "native": {}
    },
    {
      "_id": "info.currentTitles",
      "type": "state",
      "common": {
        "role": "info.titles",
        "name": "Current Titles",
        "type": "string",
        "read": true,
        "write": false
      },
      "native": {}
    },
    {
      "_id": "info.activeTitleName",
      "type": "state",
      "common": {
        "role": "name.title",
        "name": "Active title name",
        "type": "string",
        "read": true,
        "write": false
      },
      "native": {}
    },
    {
      "_id": "info.activeTitleId",
      "type": "state",
      "common": {
        "role": "id.title",
        "name": "Active title id",
        "type": "string",
        "read": true,
        "write": false
      },
      "native": {}
    },
    {
      "_id": "info.activeTitleType",
      "type": "state",
      "common": {
        "role": "name.type",
        "name": "Active title type",
        "type": "string",
        "read": true,
        "write": false
      },
      "native": {}
    }
  ]
}
